cauldron_hedgenull/__init__.py
cauldron_hedgenull/cauldron.py
cauldron_hedgenull-0.0.1.dist-info/LICENSE
cauldron_hedgenull-0.0.1.dist-info/METADATA
cauldron_hedgenull-0.0.1.dist-info/WHEEL
cauldron_hedgenull-0.0.1.dist-info/top_level.txt
cauldron_hedgenull-0.0.1.dist-info/RECORD
