Metadata-Version: 2.1
Name: cauldron-hedgenull
Version: 0.0.1
Summary: A small example package
Author-email: Example Author <author@example.com>
License: Copyright (c) 2018 The Python Packaging Authority        
Project-URL: Homepage, https://github.com/hedgenull/cauldron
Project-URL: Bug Tracker, https://github.com/hedgenull/cauldron/issues
Classifier: Programming Language :: Python :: 3
Classifier: License :: OSI Approved :: MIT License
Classifier: Operating System :: OS Independent
Requires-Python: >=3.7
License-File: LICENSE
